mijnbib/__init__.py
mijnbib/__main__.py
mijnbib/const.py
mijnbib/errors.py
mijnbib/login_handlers.py
mijnbib/mijnbibliotheek.py
mijnbib/models.py
mijnbib/parsers.py
mijnbib-0.10.3.dist-info/WHEEL
mijnbib-0.10.3.dist-info/entry_points.txt
mijnbib-0.10.3.dist-info/METADATA
mijnbib-0.10.3.dist-info/RECORD
