Metadata-Version: 2.3
Name: mijnbib
Version: 0.10.3
Summary: Python API voor de website mijn.bibliotheek.be
Keywords: mijn bibliotheek,bibliotheek
Author: Ward Van Heddeghem
Author-email: Ward Van Heddeghem <wardvh@fastmail.fm>
License: MIT License
Classifier: License :: OSI Approved :: MIT License
Classifier: Programming Language :: Python
Classifier: Programming Language :: Python :: 3
Requires-Dist: beautifulsoup4>=4.14.3
Requires-Dist: requests>=2.32.3
Requires-Python: >=3.8
Project-URL: Changelog, https://github.com/wvanhed/mijnbib/blob/main/changelog.md
Project-URL: Homepage, https://github.com/wvanhed/mijnbib
